bnnsurv/__init__.py
bnnsurv/models.py
bnnsurv/utility.py
bnnsurv-0.1.3.dist-info/LICENSE
bnnsurv-0.1.3.dist-info/METADATA
bnnsurv-0.1.3.dist-info/WHEEL
bnnsurv-0.1.3.dist-info/top_level.txt
bnnsurv-0.1.3.dist-info/RECORD
