Metadata-Version: 2.1
Name: bnnsurv
Version: 0.1.3
Summary: TensorFlow 2.x Bayesian Neural Network for Survival Analysis
Home-page: https://github.com/thecml/UE-BNNSurv
Author: Christian Marius Lillelund
Author-email: chr1000@gmail.com
License: UNKNOWN
Keywords: Deep Learning,Neural Network,Bayesian Learning,Survival Analysis
Platform: UNKNOWN
Classifier: Programming Language :: Python :: 3
Classifier: Programming Language :: Python :: 3.6
Classifier: Programming Language :: Python :: 3.7
Classifier: Programming Language :: Python :: 3.8
Classifier: Programming Language :: Python :: 3.9
Classifier: License :: OSI Approved :: MIT License
Classifier: Intended Audience :: Developers
Classifier: Intended Audience :: Other Audience
Classifier: Intended Audience :: Science/Research
Classifier: Intended Audience :: Education
Classifier: Topic :: Scientific/Engineering :: Artificial Intelligence
Classifier: Operating System :: OS Independent
Requires-Dist: numpy (~=1.22)
Requires-Dist: scikit-survival (~=0.22)
Requires-Dist: tensorflow (>=2.11)
Requires-Dist: tensorflow-probability (>=0.19)
